rtl/low_power_alu.v
module low_power_alu #(
    parameter WIDTH = 16
)(
    input  wire                  clk,
    input  wire                  rst_n,

    input  wire                  en,
    input  wire                  lp_mode,

    input  wire [WIDTH-1:0]      A,
    input  wire [WIDTH-1:0]      B,
    input  wire [3:0]            opcode,

    output reg  [WIDTH-1:0]      result,
    output reg                   zero,
    output reg                   carry,
    output reg                   overflow,
    output reg                   negative
);

    // Operand Isolation
    wire [WIDTH-1:0] A_iso;
    wire [WIDTH-1:0] B_iso;

    assign A_iso = en ? A : {WIDTH{1'b0}};
    assign B_iso = en ? B : {WIDTH{1'b0}};

    // Shift Amount Logic
    localparam SHIFT_W =
        (WIDTH <= 2 ) ? 1 :
        (WIDTH <= 4 ) ? 2 :
        (WIDTH <= 8 ) ? 3 :
        (WIDTH <= 16) ? 4 :
        (WIDTH <= 32) ? 5 : 6;

    wire [SHIFT_W-1:0] shift_amt;

    assign shift_amt =
        lp_mode ?
        B_iso[1:0] :
        B_iso[SHIFT_W-1:0];

    reg [WIDTH-1:0] alu_result;
    reg carry_next;
    reg overflow_next;
    reg [WIDTH:0] temp;

    always @(*) begin

        alu_result    = {WIDTH{1'b0}};
        carry_next    = 1'b0;
        overflow_next = 1'b0;
        temp          = {(WIDTH+1){1'b0}};

        case(opcode)

            // ADD
            4'b0000: begin
                temp = A_iso + B_iso;

                alu_result = temp[WIDTH-1:0];
                carry_next = temp[WIDTH];

                overflow_next =
                    (~A_iso[WIDTH-1] &
                     ~B_iso[WIDTH-1] &
                      alu_result[WIDTH-1]) |
                    ( A_iso[WIDTH-1] &
                      B_iso[WIDTH-1] &
                     ~alu_result[WIDTH-1]);
            end

            // SUB
            4'b0001: begin
                temp = A_iso - B_iso;

                alu_result = temp[WIDTH-1:0];
                carry_next = temp[WIDTH];

                overflow_next =
                    (~A_iso[WIDTH-1] &
                      B_iso[WIDTH-1] &
                      alu_result[WIDTH-1]) |
                    ( A_iso[WIDTH-1] &
                     ~B_iso[WIDTH-1] &
                     ~alu_result[WIDTH-1]);
            end

            // AND
            4'b0010:
                alu_result = A_iso & B_iso;

            // OR
            4'b0011:
                alu_result = A_iso | B_iso;

            // XOR
            4'b0100:
                alu_result = A_iso ^ B_iso;

            // NOT
            4'b0101:
                alu_result = ~A_iso;

            // SHIFT LEFT
            4'b0110:
                alu_result = A_iso << shift_amt;

            // SHIFT RIGHT
            4'b0111:
                alu_result = A_iso >> shift_amt;

            // INC
            4'b1000: begin
                temp = A_iso + 1'b1;
                alu_result = temp[WIDTH-1:0];
                carry_next = temp[WIDTH];
            end

            // DEC
            4'b1001: begin
                temp = A_iso - 1'b1;
                alu_result = temp[WIDTH-1:0];
                carry_next = temp[WIDTH];
            end

            // COMPARE
            4'b1010:
                alu_result =
                    (A_iso == B_iso) ?
                    {{(WIDTH-1){1'b0}},1'b1} :
                    {WIDTH{1'b0}};

            default: begin
                alu_result    = {WIDTH{1'b0}};
                carry_next    = 1'b0;
                overflow_next = 1'b0;
            end

        endcase
    end

    // Registered Outputs
    always @(posedge clk or negedge rst_n) begin

        if(!rst_n) begin

            result   <= {WIDTH{1'b0}};
            carry    <= 1'b0;
            overflow <= 1'b0;
            zero     <= 1'b0;
            negative <= 1'b0;

        end
        else if(en) begin

            result   <= alu_result;
            carry    <= carry_next;
            overflow <= overflow_next;

            zero     <= (alu_result == 0);
            negative <= alu_result[WIDTH-1];

        end

    end

endmodule

tb/alu_tb.v
`timescale 1ns/1ps

module alu_tb;

parameter WIDTH = 16;

reg clk;
reg rst_n;

reg en;
reg lp_mode;

reg [WIDTH-1:0] A;
reg [WIDTH-1:0] B;
reg [3:0] opcode;

wire [WIDTH-1:0] result;
wire zero;
wire carry;
wire overflow;
wire negative;

integer pass_count;
integer fail_count;

low_power_alu #(
    .WIDTH(WIDTH)
)
dut (
    .clk(clk),
    .rst_n(rst_n),
    .en(en),
    .lp_mode(lp_mode),
    .A(A),
    .B(B),
    .opcode(opcode),
    .result(result),
    .zero(zero),
    .carry(carry),
    .overflow(overflow),
    .negative(negative)
);

initial begin
    clk = 0;
    forever #5 clk = ~clk;
end

task check_result;
input [WIDTH-1:0] expected;
begin
    @(posedge clk);
    #1;

    if(result === expected) begin
        pass_count = pass_count + 1;
        $display("[PASS] opcode=%b expected=%h got=%h",
                 opcode, expected, result);
    end
    else begin
        fail_count = fail_count + 1;
        $display("[FAIL] opcode=%b expected=%h got=%h",
                 opcode, expected, result);
    end
end
endtask

initial begin

    $dumpfile("alu_power.vcd");
    $dumpvars(0, alu_tb);

    pass_count = 0;
    fail_count = 0;

    rst_n = 0;
    en = 0;
    lp_mode = 0;
    A = 0;
    B = 0;
    opcode = 0;

    repeat(3) @(posedge clk);

    rst_n = 1;
    en = 1;

    A = 16'd25;
    B = 16'd10;
    opcode = 4'b0000;
    check_result(16'd35);

    A = 16'd50;
    B = 16'd15;
    opcode = 4'b0001;
    check_result(16'd35);

    A = 16'h00FF;
    B = 16'h0F0F;
    opcode = 4'b0010;
    check_result(16'h000F);

    opcode = 4'b0011;
    check_result(16'h0FFF);

    opcode = 4'b0100;
    check_result(16'h0FF0);

    A = 16'h00FF;
    opcode = 4'b0101;
    check_result(~16'h00FF);

    A = 16'h0003;
    B = 16'd2;
    opcode = 4'b0110;
    check_result(16'h000C);

    opcode = 4'b0111;
    check_result(16'h0000);

    A = 16'd99;
    opcode = 4'b1000;
    check_result(16'd100);

    opcode = 4'b1001;
    check_result(16'd98);

    A = 16'h1234;
    B = 16'h1234;
    opcode = 4'b1010;
    check_result(16'h0001);

    A = 16'd5;
    B = 16'd5;
    opcode = 4'b0001;

    @(posedge clk);
    #1;

    if(zero)
        $display("[PASS] ZERO FLAG");
    else
        $display("[FAIL] ZERO FLAG");

    A = 16'd5;
    B = 16'd10;
    opcode = 4'b0001;

    @(posedge clk);
    #1;

    if(negative)
        $display("[PASS] NEGATIVE FLAG");
    else
        $display("[FAIL] NEGATIVE FLAG");

    en = 0;
    A = 16'hFFFF;
    B = 16'hFFFF;
    opcode = 4'b0000;

    repeat(2) @(posedge clk);

    en = 1;
    lp_mode = 1;

    A = 16'h1234;
    B = 16'h0007;
    opcode = 4'b0110;

    repeat(2) @(posedge clk);

    repeat(100) begin
        A = $random;
        B = $random;
        opcode = $random % 11;
        @(posedge clk);
    end

    $display("--------------------------------");
    $display("PASS COUNT = %0d", pass_count);
    $display("FAIL COUNT = %0d", fail_count);
    $display("--------------------------------");

    $finish;

end

endmodule

waveforms/alu_power.vcd
$date
	Wed Jun 17 13:30:50 2026
$end
$version
	Icarus Verilog
$end
$timescale
	1ps
$end
$scope module alu_tb $end
$var wire 1 ! zero $end
$var wire 16 " result [15:0] $end
$var wire 1 # overflow $end
$var wire 1 $ negative $end
$var wire 1 % carry $end
$var parameter 32 & WIDTH $end
$var reg 16 ' A [15:0] $end
$var reg 16 ( B [15:0] $end
$var reg 1 ) clk $end
$var reg 1 * en $end
$var reg 1 + lp_mode $end
$var reg 4 , opcode [3:0] $end
$var reg 1 - rst_n $end
$var integer 32 . fail_count [31:0] $end
$var integer 32 / pass_count [31:0] $end
$scope module dut $end
$var wire 16 0 A [15:0] $end
$var wire 16 1 B [15:0] $end
$var wire 1 ) clk $end
$var wire 1 * en $end
$var wire 1 + lp_mode $end
$var wire 4 2 opcode [3:0] $end
$var wire 1 - rst_n $end
$var wire 4 3 shift_amt [3:0] $end
$var wire 16 4 B_iso [15:0] $end
$var wire 16 5 A_iso [15:0] $end
$var parameter 32 6 SHIFT_W $end
$var parameter 32 7 WIDTH $end
$var reg 16 8 alu_result [15:0] $end
$var reg 1 % carry $end
$var reg 1 9 carry_next $end
$var reg 1 $ negative $end
$var reg 1 # overflow $end
$var reg 1 : overflow_next $end
$var reg 16 ; result [15:0] $end
$var reg 17 < temp [16:0] $end
$var reg 1 ! zero $end
$upscope $end
$scope task check_result $end
$var reg 16 = expected [15:0] $end
$upscope $end
$upscope $end
$enddefinitions $end
$comment Show the parameter values. $end
$dumpall
b10000 7
b100 6
b10000 &
$end
#0
$dumpvars
bx =
b0 <
b0 ;
0:
09
b0 8
b0 5
b0 4
b0 3
b0 2
b0 1
b0 0
b0 /
b0 .
0-
b0 ,
0+
0*
0)
b0 (
b0 '
0%
0$
0#
b0 "
0!
$end
#5000
1)
#10000
0)
#15000
1)
#20000
0)
#25000
1!
b1010 3
b100011 8
b100011 <
b11001 5
b1010 4
b100011 =
b1010 (
b1010 1
b11001 '
b11001 0
1*
1-
1)
#30000
0)
#35000
0!
b100011 "
b100011 ;
1)
#36000
b1111 3
b100011 <
b100011 8
b1111 4
b110010 5
b1 ,
b1 2
b1111 (
b1111 1
b110010 '
b110010 0
b1 /
#40000
0)
#45000
1)
#46000
b0 <
b1111 8
b111100001111 4
b11111111 5
b1111 =
b10 ,
b10 2
b111100001111 (
b111100001111 1
b11111111 '
b11111111 0
b10 /
#50000
0)
#55000
b1111 "
b1111 ;
1)
#56000
b111111111111 8
b111111111111 =
b11 ,
b11 2
b11 /
#60000
0)
#65000
b111111111111 "
b111111111111 ;
1)
#66000
b111111110000 8
b111111110000 =
b100 ,
b100 2
b100 /
#70000
0)
#75000
b111111110000 "
b111111110000 ;
1)
#76000
b1111111100000000 8
b1111111100000000 =
b101 ,
b101 2
b101 /
#80000
0)
#85000
1$
b1111111100000000 "
b1111111100000000 ;
1)
#86000
b10 3
b1100 8
b10 4
b11 5
b1100 =
b110 ,
b110 2
b10 (
b10 1
b11 '
b11 0
b110 /
#90000
0)
#95000
0$
b1100 "
b1100 ;
1)
#96000
b0 8
b0 =
b111 ,
b111 2
b111 /
#100000
0)
#105000
1!
b0 "
b0 ;
1)
#106000
b1100100 8
b1100100 <
b1100011 5
b1100100 =
b1000 ,
b1000 2
b1100011 '
b1100011 0
b1000 /
#110000
0)
#115000
0!
b1100100 "
b1100100 ;
1)
#116000
b1100010 <
b1100010 8
b1100010 =
b1001 ,
b1001 2
b1001 /
#120000
0)
#125000
b1100010 "
b1100010 ;
1)
#126000
b100 3
b0 <
b1 8
b1001000110100 4
b1001000110100 5
b1 =
b1010 ,
b1010 2
b1001000110100 (
b1001000110100 1
b1001000110100 '
b1001000110100 0
b1010 /
#130000
0)
#135000
b1 "
b1 ;
1)
#136000
b101 3
b0 8
b101 4
b101 5
b1 ,
b1 2
b101 (
b101 1
b101 '
b101 0
b1011 /
#140000
0)
#145000
1!
b0 "
b0 ;
1)
#146000
b1010 3
19
b1111111111111011 8
b11111111111111011 <
b1010 4
b1010 (
b1010 1
#150000
0)
#155000
1$
0!
1%
b1111111111111011 "
b1111111111111011 ;
1)
#156000
b0 3
b0 <
09
b0 8
b0 5
b0 4
b0 ,
b0 2
b1111111111111111 (
b1111111111111111 1
b1111111111111111 '
b1111111111111111 0
0*
#160000
0)
#165000
1)
#170000
0)
#175000
0$
1!
0%
b0 "
b0 ;
b11 3
b1001000110100000 8
b1001000110100 5
b111 4
b110 ,
b110 2
b111 (
b111 1
b1001000110100 '
b1001000110100 0
1+
1*
1)
#180000
0)
#185000
1$
0!
b1001000110100000 "
b1001000110100000 ;
1)
#190000
0)
#195000
b1 3
b0 8
b101111010000001 4
b11010100100100 5
b1110 ,
b1110 2
b101111010000001 (
b101111010000001 1
b11010100100100 '
b11010100100100 0
1)
#200000
0)
#205000
0$
1!
b0 "
b0 ;
b101011001100010 8
b101011001100010 <
b111101100001101 4
b101011001100011 5
b1001 ,
b1001 2
b111101100001101 (
b111101100001101 1
b101011001100011 '
b101011001100011 0
1)
#210000
0)
#215000
0!
b101011001100010 "
b101011001100010 ;
b10 3
b1000010001100100 <
b1000010001100100 8
b101001000010010 4
b1000010001100101 5
b101001000010010 (
b101001000010010 1
b1000010001100101 '
b1000010001100101 0
1)
#220000
0)
#225000
1$
b1000010001100100 "
b1000010001100100 ;
b0 <
b11001011110010 8
b1111000101110110 4
b1100110100001101 5
b101 ,
b101 2
b1111000101110110 (
b1111000101110110 1
b1100110100001101 '
b1100110100001101 0
1)
#230000
0)
#235000
0$
b11001011110010 "
b11001011110010 ;
b0 3
b101011111101101 8
b1111011110001100 4
b101011111101101 5
b110 ,
b110 2
b1111011110001100 (
b1111011110001100 1
b101011111101101 '
b101011111101101 0
1)
#240000
0)
#245000
b101011111101101 "
b101011111101101 ;
b1 3
b0 8
b1000010011000101 4
b10010011000110 5
b1101 ,
b1101 2
b1000010011000101 (
b1000010011000101 1
b10010011000110 '
b10010011000110 0
1)
#250000
0)
#255000
1!
b0 "
b0 ;
b11 3
b111001001110111 4
b1111011111100101 5
b1110 ,
b1110 2
b111001001110111 (
b111001001110111 1
b1111011111100101 '
b1111011111100101 0
1)
#260000
0)
#265000
b10 3
b110100111110010 4
b1101101110001111 5
b110100111110010 (
b110100111110010 1
b1101101110001111 '
b1101101110001111 0
1)
#270000
0)
#275000
b1 3
b100101011000000 8
b100111011000101 4
b111101011101000 5
b10 ,
b10 2
b100111011000101 (
b100111011000101 1
b111101011101000 '
b111101011101000 0
1)
#280000
0)
#285000
0!
b100101011000000 "
b100101011000000 ;
b0 8
b101100000101101 4
b10100010111101 5
b1101 ,
b1101 2
b101100000101101 (
b101100000101101 1
b10100010111101 '
b10100010111101 0
1)
#290000
0)
#295000
1!
b0 "
b0 ;
b10 3
b1000100110001100 8
b1000011100001010 4
b110001001100011 5
b110 ,
b110 2
b1000011100001010 (
b1000011100001010 1
b110001001100011 '
b110001001100011 0
1)
#300000
0)
#305000
1$
0!
b1000100110001100 "
b1000100110001100 ;
b1000010010000000 8
b100010110101010 4
b10000100100000 5
b100010110101010 (
b100010110101010 1
b10000100100000 '
b10000100100000 0
1)
#310000
0)
#315000
b1000010010000000 "
b1000010010000000 ;
b11 3
b0 8
b1011100000010011 4
b11111010010110 5
b1110 ,
b1110 2
b1011100000010011 (
b1011100000010011 1
b11111010010110 '
b11111010010110 0
1)
#320000
0)
#325000
0$
1!
b0 "
b0 ;
b1101110101101011 4
b1101011001010011 5
b1100 ,
b1100 2
b1101110101101011 (
b1101110101101011 1
b1101011001010011 '
b1101011001010011 0
1)
#330000
0)
#335000
b10 3
b101000000010 8
b11111010101110 4
b100101000000010 5
b10 ,
b10 2
b11111010101110 (
b11111010101110 1
b100101000000010 '
b100101000000010 0
1)
#340000
0)
#345000
0!
b101000000010 "
b101000000010 ;
b11 3
b10100110101100 <
b10100110101100 8
b100100100100011 4
b111001011001111 5
b1 ,
b1 2
b100100100100011 (
b100100100100011 1
b111001011001111 '
b111001011001111 0
1)
#350000
0)
#355000
b10100110101100 "
b10100110101100 ;
b0 3
b0 <
b101011001010 8
b100110000111100 4
b101011001010 5
b111 ,
b111 2
b100110000111100 (
b100110000111100 1
b101011001010 '
b101011001010 0
1)
#360000
0)
#365000
b101011001010 "
b101011001010 ;
b1 3
b1100001100010100 8
b1011001101000001 4
b110000110001010 5
b110 ,
b110 2
b1011001101000001 (
b1011001101000001 1
b110000110001010 '
b110000110001010 0
1)
#370000
0)
#375000
1$
b1100001100010100 "
b1100001100010100 ;
b1111001111111001 8
b1001010001001 4
b1111001101111000 5
b11 ,
b11 2
b1001010001001 (
b1001010001001 1
b1111001101111000 '
b1111001101111000 0
1)
#380000
0)
#385000
b1111001111111001 "
b1111001111111001 ;
b10 3
b110010110110111 <
b110010110110111 8
b1111100111000110 4
b110010110110110 5
b1000 ,
b1000 2
b1111100111000110 (
b1111100111000110 1
b110010110110110 '
b110010110110110 0
1)
#390000
0)
#395000
0$
b110010110110111 "
b110010110110111 ;
b1101111111100110 <
b1101111111100110 8
b1101110100101010 4
b1010111100 5
b0 ,
b0 2
b1101110100101010 (
b1101110100101010 1
b1010111100 '
b1010111100 0
1)
#400000
0)
#405000
1$
b1101111111100110 "
b1101111111100110 ;
b1 3
1:
b111110011101100 <
b111110011101100 8
b100000110000101 4
b1011111001110001 5
b1 ,
b1 2
b100000110000101 (
b100000110000101 1
b1011111001110001 '
b1011111001110001 0
1)
#410000
0)
#415000
0$
1#
b111110011101100 "
b111110011101100 ;
b10 3
b0 <
0:
b1100000001110 8
b11001100111010 4
b110000000111011 5
b111 ,
b111 2
b11001100111010 (
b11001100111010 1
b110000000111011 '
b110000000111011 0
1)
#420000
0)
#425000
0#
b1100000001110 "
b1100000001110 ;
b1 3
b0 8
b1001101111110001 4
b100101100010101 5
b1010 ,
b1010 2
b1001101111110001 (
b1001101111110001 1
b100101100010101 '
b100101100010101 0
1)
#430000
0)
#435000
1!
b0 "
b0 ;
b0 3
b1111111101101110 8
b1111101101001100 4
b11101100010 5
b11 ,
b11 2
b1111101101001100 (
b1111101101001100 1
b11101100010 '
b11101100010 0
1)
#440000
0)
#445000
1$
0!
b1111111101101110 "
b1111111101101110 ;
b0 8
b1010100111111000 4
b1010000110001111 5
b1101 ,
b1101 2
b1010100111111000 (
b1010100111111000 1
b1010000110001111 '
b1010000110001111 0
1)
#450000
0)
#455000
0$
1!
b0 "
b0 ;
b1110101011111011 8
b1110101011111011 <
b1001010001011100 4
b101011010011111 5
b0 ,
b0 2
b1001010001011100 (
b1001010001011100 1
b101011010011111 '
b101011010011111 0
1)
#460000
0)
#465000
1$
0!
b1110101011111011 "
b1110101011111011 ;
b1 3
b0 <
b0 8
b11001001001001 4
b11011110001001 5
b1011 ,
b1011 2
b11001001001001 (
b11001001001001 1
b11011110001001 '
b11011110001001 0
1)
#470000
0)
#475000
0$
1!
b0 "
b0 ;
b1000000110101110 8
b1111110001010001 4
b1100000011010111 5
b110 ,
b110 2
b1111110001010001 (
b1111110001010001 1
b1100000011010111 '
b1100000011010111 0
1)
#480000
0)
#485000
1$
0!
b1000000110101110 "
b1000000110101110 ;
b10 3
b1000000011110011 8
b1100111011000010 4
b111111100001100 5
b101 ,
b101 2
b1100111011000010 (
b1100111011000010 1
b111111100001100 '
b111111100001100 0
1)
#490000
0)
#495000
b1000000011110011 "
b1000000011110011 ;
b1 3
b1111111101111111 8
b1110110100111101 4
b101101001110111 5
b11 ,
b11 2
b1110110100111101 (
b1110110100111101 1
b101101001110111 '
b101101001110111 0
1)
#500000
0)
#505000
b1111111101111111 "
b1111111101111111 ;
b1111111110000001 8
b1000000101101101 4
b1111110 5
b101 ,
b101 2
b1000000101101101 (
b1000000101101101 1
b1111110 '
b1111110 0
1)
#510000
0)
#515000
b1111111110000001 "
b1111111110000001 ;
b11 3
b111000011100000 8
b1111011011010011 4
b1000111100011111 5
b1111011011010011 (
b1111011011010011 1
b1000111100011111 '
b1000111100011111 0
1)
#520000
0)
#525000
0$
b111000011100000 "
b111000011100000 ;
b100001011000 8
b101100101011011 4
b1000100001111000 5
b10 ,
b10 2
b101100101011011 (
b101100101011011 1
b1000100001111000 '
b1000100001111000 0
1)
#530000
0)
#535000
b100001011000 "
b100001011000 ;
b10 3
b1010111000101010 8
b1010111100101010 4
b1010111000111111 5
b1010111100101010 (
b1010111100101010 1
b1010111000111111 '
b1010111000111111 0
1)
#540000
0)
#545000
1$
b1010111000101010 "
b1010111000101010 ;
b0 8
b110010001110 4
b11100010000110 5
b1111 ,
b1111 2
b110010001110 (
b110010001110 1
b11100010000110 '
b11100010000110 0
1)
#550000
0)
#555000
0$
1!
b0 "
b0 ;
b10010111011100 8
b1011110000100110 4
b1001100111111010 5
b100 ,
b100 2
b1011110000100110 (
b1011110000100110 1
b1001100111111010 '
b1001100111111010 0
1)
#560000
0)
#565000
0!
b10010111011100 "
b10010111011100 ;
b11 3
b1011010010100 8
b1010100000101111 4
b1011010010100011 5
b111 ,
b111 2
b1010100000101111 (
b1010100000101111 1
b1011010010100011 '
b1011010010100011 0
1)
#570000
0)
#575000
b1011010010100 "
b1011010010100 ;
b0 3
b101111101011111 8
b110101000100 4
b101011001011111 5
b11 ,
b11 2
b110101000100 (
b110101000100 1
b101011001011111 '
b101011001011111 0
1)
#580000
0)
#585000
b101111101011111 "
b101111101011111 ;
b10 3
b1101111100101 <
b1101111100101 8
b1101011100110 4
b11011011001011 5
b1 ,
b1 2
b1101011100110 (
b1101011100110 1
b11011011001011 '
b11011011001011 0
1)
#590000
0)
#595000
b1101111100101 "
b1101111100101 ;
b1 3
b0 <
b0 8
b1110001011101101 4
b1100000100101001 5
b1011 ,
b1011 2
b1110001011101101 (
b1110001011101101 1
b1100000100101001 '
b1100000100101001 0
1)
#600000
0)
#605000
1!
b0 "
b0 ;
b1011011001100100 8
b1011011001100100 <
b1110001010110101 4
b1011011001100101 5
b1001 ,
b1001 2
b1110001010110101 (
b1110001010110101 1
b1011011001100101 '
b1011011001100101 0
1)
#610000
0)
#615000
1$
0!
b1011011001100100 "
b1011011001100100 ;
b0 3
b0 <
b1100101111001 8
b1111111101000100 4
b1100101111001 5
b111 ,
b111 2
b1111111101000100 (
b1111111101000100 1
b1100101111001 '
b1100101111001 0
1)
#620000
0)
#625000
0$
b1100101111001 "
b1100101111001 ;
b11 3
b101100101011 <
b101100101011 8
b1010110110101011 4
b101100101010 5
b1000 ,
b1000 2
b1010110110101011 (
b1010110110101011 1
b101100101010 '
b101100101010 0
1)
#630000
0)
#635000
b101100101011 "
b101100101011 ;
b10 3
b0 <
b0 8
b1011110010011010 4
b1010110111011100 5
b1100 ,
b1100 2
b1011110010011010 (
b1011110010011010 1
b1010110111011100 '
b1010110111011100 0
1)
#640000
0)
#645000
1!
b0 "
b0 ;
b1110111110010101 8
b1110110101010110 4
b1011000011 5
b100 ,
b100 2
b1110110101010110 (
b1110110101010110 1
b1011000011 '
b1011000011 0
1)
#650000
0)
#655000
1$
0!
b1110111110010101 "
b1110111110010101 ;
b11010000000010 8
b11010000001010 4
b111011001100111 5
b10 ,
b10 2
b11010000001010 (
b11010000001010 1
b111011001100111 '
b111011001100111 0
1)
#660000
0)
#665000
0$
b11010000000010 "
b11010000000010 ;
b1 3
1:
19
b10001000110110001 <
b1000110110001 8
b1000011101111001 4
b1000101000111000 5
b0 ,
b0 2
b1000011101111001 (
b1000011101111001 1
b1000101000111000 '
b1000101000111000 0
1)
#670000
0)
#675000
1#
1%
b1000110110001 "
b1000110110001 ;
b11 3
b0 <
0:
09
b0 8
b101110110010011 4
b1011111110010100 5
b1100 ,
b1100 2
b101110110010011 (
b101110110010011 1
b1011111110010100 '
b1011111110010100 0
1)
#680000
0)
#685000
1!
0#
0%
b0 "
b0 ;
b110100111011011 4
b1100101001011001 5
b1110 ,
b1110 2
b110100111011011 (
b110100111011011 1
b1100101001011001 '
b1100101001011001 0
1)
#690000
0)
#695000
b1 3
b10011001101101 4
b1011011111011001 5
b1010 ,
b1010 2
b10011001101101 (
b10011001101101 1
b1011011111011001 '
b1011011111011001 0
1)
#700000
0)
#705000
b10 3
b110110111111110 8
b10110110110110 4
b100100111001010 5
b11 ,
b11 2
b10110110110110 (
b10110110110110 1
b100100111001010 '
b100100111001010 0
1)
#710000
0)
#715000
0!
b110110111111110 "
b110110111111110 ;
b0 3
b1101001000110 8
b1001101100000100 4
b1101001000110 5
b111 ,
b111 2
b1001101100000100 (
b1001101100000100 1
b1101001000110 '
b1101001000110 0
1)
#720000
0)
#725000
b1101001000110 "
b1101001000110 ;
b11101101001 8
b1011101010110100 4
b11101101001 5
b110 ,
b110 2
b1011101010110100 (
b1011101010110100 1
b11101101001 '
b11101101001 0
1)
#730000
0)
#735000
b11101101001 "
b11101101001 ;
b1 3
b110110010010100 8
b10000101101 4
b1101100100101000 5
b111 ,
b111 2
b10000101101 (
b10000101101 1
b1101100100101000 '
b1101100100101000 0
1)
#740000
0)
#745000
b110110010010100 "
b110110010010100 ;
b0 3
b0 8
b1110010000001000 4
b1001110000101110 5
b1010 ,
b1010 2
b1110010000001000 (
b1110010000001000 1
b1001110000101110 '
b1001110000101110 0
1)
#750000
0)
#755000
1!
b0 "
b0 ;
b1 3
b1010111000100110 8
b1010111000100110 <
b11100101001 4
b1010011011111101 5
b0 ,
b0 2
b11100101001 (
b11100101001 1
b1010011011111101 '
b1010011011111101 0
1)
#760000
0)
#765000
1$
0!
b1010111000100110 "
b1010111000100110 ;
b10 3
b0 <
b0 8
b100011011010 4
b110011110000110 5
b1101 ,
b1101 2
b100011011010 (
b100011011010 1
b110011110000110 '
b110011110000110 0
1)
#770000
0)
#775000
0$
1!
b0 "
b0 ;
b0 3
b1100010001110000 4
b1010011101100110 5
b1100010001110000 (
b1100010001110000 1
b1010011101100110 '
b1010011101100110 0
1)
#780000
0)
#785000
b10 3
b10011001101110 8
b1011001101011110 4
b1001100110111010 5
b111 ,
b111 2
b1011001101011110 (
b1011001101011110 1
b1001100110111010 '
b1001100110111010 0
1)
#790000
0)
#795000
0!
b10011001101110 "
b10011001101110 ;
b0 8
b1111011000011010 4
b10111010101 5
b1110 ,
b1110 2
b1111011000011010 (
b1111011000011010 1
b10111010101 '
b10111010101 0
1)
#800000
0)
#805000
1!
b0 "
b0 ;
b110000100111000 8
b110000100111000 <
b11011110010110 4
b110000100110111 5
b1000 ,
b1000 2
b11011110010110 (
b11011110010110 1
b110000100110111 '
b110000100110111 0
1)
#810000
0)
#815000
0!
b110000100111000 "
b110000100111000 ;
b0 <
b110000011011001 8
b1101010110110 4
b1001111100100110 5
b101 ,
b101 2
b1101010110110 (
b1101010110110 1
b1001111100100110 '
b1001111100100110 0
1)
#820000
0)
#825000
b110000011011001 "
b110000011011001 ;
b11110000100 8
b101011110000110 4
b111111011100 5
b10 ,
b10 2
b101011110000110 (
b101011110000110 1
b111111011100 '
b111111011100 0
1)
#830000
0)
#835000
b11110000100 "
b11110000100 ;
b11 3
b0 8
b1000000011011011 4
b1001101101111110 5
b1100 ,
b1100 2
b1000000011011011 (
b1000000011011011 1
b1001101101111110 '
b1001101101111110 0
1)
#840000
0)
#845000
1!
b0 "
b0 ;
b10 3
b101011011110 8
b1110010011111010 4
b10101101111001 5
b111 ,
b111 2
b1110010011111010 (
b1110010011111010 1
b10101101111001 '
b10101101111001 0
1)
#850000
0)
#855000
0!
b101011011110 "
b101011011110 ;
b1 3
b1001000101110 8
b111100010100001 4
b100100010111 5
b110 ,
b110 2
b111100010100001 (
b111100010100001 1
b100100010111 '
b100100010111 0
1)
#860000
0)
#865000
b1001000101110 "
b1001000101110 ;
b0 8
b101100111110101 4
b1001011001010000 5
b1110 ,
b1110 2
b101100111110101 (
b101100111110101 1
b1001011001010000 '
b1001011001010000 0
1)
#870000
0)
#875000
1!
b0 "
b0 ;
b1000101000101010 8
b1000101000101010 <
b111010111000001 4
b1000101000101001 5
b1000 ,
b1000 2
b111010111000001 (
b111010111000001 1
b1000101000101001 '
b1000101000101001 0
1)
#880000
0)
#885000
1$
0!
b1000101000101010 "
b1000101000101010 ;
b11 3
b0 <
b0 8
b111101101001011 4
b1011010010011000 5
b1101 ,
b1101 2
b111101101001011 (
b111101101001011 1
b1011010010011000 '
b1011010010011000 0
1)
#890000
0)
#895000
0$
1!
b0 "
b0 ;
b10 3
b1110011011101011 8
b1110011011101011 <
b1011010001010 4
b1110011011101100 5
b1001 ,
b1001 2
b1011010001010 (
b1011010001010 1
b1110011011101100 '
b1110011011101100 0
1)
#900000
0)
#905000
1$
0!
b1110011011101011 "
b1110011011101011 ;
b1 3
b1000000010101001 <
b1000000010101001 8
b1111110110101001 4
b1000000010101000 5
b1000 ,
b1000 2
b1111110110101001 (
b1111110110101001 1
b1000000010101000 '
b1000000010101000 0
1)
#910000
0)
#915000
b1000000010101001 "
b1000000010101001 ;
b10 3
b0 <
b0 8
b110011011100110 4
b1011100100001110 5
b1100 ,
b1100 2
b110011011100110 (
b110011011100110 1
b1011100100001110 '
b1011100100001110 0
1)
#920000
0)
#925000
0$
1!
b0 "
b0 ;
b1101010010101000 8
b1110100101010 4
b1011010100101010 5
b110 ,
b110 2
b1110100101010 (
b1110100101010 1
b1011010100101010 '
b1011010100101010 0
1)
#930000
0)
#935000
1$
0!
b1101010010101000 "
b1101010010101000 ;
b0 3
b1111111110011111 <
b1111111110011111 8
b1110011000111000 4
b1111111110011110 5
b1000 ,
b1000 2
b1110011000111000 (
b1110011000111000 1
b1111111110011110 '
b1111111110011110 0
1)
#940000
0)
#945000
b1111111110011111 "
b1111111110011111 ;
b10 3
b0 <
b100000111001000 8
b100010111001010 4
b1110001111001000 5
b10 ,
b10 2
b100010111001010 (
b100010111001010 1
b1110001111001000 '
b1110001111001000 0
1)
#950000
0)
#955000
0$
b100000111001000 "
b100000111001000 ;
b11 3
b1000100001000011 8
b1010111011000111 4
b1100100101101011 5
b1010111011000111 (
b1010111011000111 1
b1100100101101011 '
b1100100101101011 0
1)
#960000
0)
#965000
1$
b1000100001000011 "
b1000100001000011 ;
b0 3
b1001110110111010 8
b1010101111000100 4
b1001110110111010 5
b111 ,
b111 2
b1010101111000100 (
b1010101111000100 1
b1001110110111010 '
b1001110110111010 0
1)
#970000
0)
#975000
b1001110110111010 "
b1001110110111010 ;
b1101101110110110 8
b1001101010110100 4
b1101001110010010 5
b11 ,
b11 2
b1001101010110100 (
b1001101010110100 1
b1101001110010010 '
b1101001110010010 0
1)
#980000
0)
#985000
b1101101110110110 "
b1101101110110110 ;
b10 3
b100001000011000 8
b1111010111111010 4
b1001000010000110 5
b110 ,
b110 2
b1111010111111010 (
b1111010111111010 1
b1001000010000110 '
b1001000010000110 0
1)
#990000
0)
#995000
0$
b100001000011000 "
b100001000011000 ;
b1 3
b100001001100100 8
b101111010111101 4
b10000100110010 5
b101111010111101 (
b101111010111101 1
b10000100110010 '
b10000100110010 0
1)
#1000000
0)
#1005000
b100001001100100 "
b100001001100100 ;
b10 3
1:
19
b10111010010101110 <
b111010010101110 8
b1100111111001010 4
b1010010011100100 5
b0 ,
b0 2
b1100111111001010 (
b1100111111001010 1
b1010010011100100 '
b1010010011100100 0
1)
#1010000
0)
